opinion_api/__init__.py
opinion_api/api_client.py
opinion_api/api_response.py
opinion_api/configuration.py
opinion_api/exceptions.py
opinion_api/opinion_api_client.py
opinion_api/rest.py
opinion_api/api/__init__.py
opinion_api/api/prediction_market_api.py
opinion_api/api/user_api.py
opinion_api/models/__init__.py
opinion_api/models/models_topic_status.py
opinion_api/models/openapi_balance_resp_open_api.py
opinion_api/models/openapi_cancel_order_request_open_api.py
opinion_api/models/openapi_cancel_order_resp_open_api.py
opinion_api/models/openapi_child_market_data_open_api.py
opinion_api/models/openapi_fee_rates_resp_open_api.py
opinion_api/models/openapi_latest_price_resp_open_api.py
opinion_api/models/openapi_market_categorical_market_id_get200_response.py
opinion_api/models/openapi_market_data_open_api.py
opinion_api/models/openapi_market_detail_resp_open_api.py
opinion_api/models/openapi_market_get200_response.py
opinion_api/models/openapi_market_list_resp_open_api.py
opinion_api/models/openapi_order_cancel_post200_response.py
opinion_api/models/openapi_order_data_open_api.py
opinion_api/models/openapi_order_detail_resp_open_api.py
opinion_api/models/openapi_order_get200_response.py
opinion_api/models/openapi_order_list_resp_open_api.py
opinion_api/models/openapi_order_order_id_get200_response.py
opinion_api/models/openapi_order_post200_response.py
opinion_api/models/openapi_orderbook_level.py
opinion_api/models/openapi_orderbook_resp_open_api.py
opinion_api/models/openapi_position_data_open_api.py
opinion_api/models/openapi_positions_get200_response.py
opinion_api/models/openapi_positions_resp_open_api.py
opinion_api/models/openapi_price_history_resp_open_api.py
opinion_api/models/openapi_price_point.py
opinion_api/models/openapi_quote_token_balance.py
opinion_api/models/openapi_quote_token_data_open_api.py
opinion_api/models/openapi_quote_token_get200_response.py
opinion_api/models/openapi_quote_token_list_resp_open_api.py
opinion_api-0.3.0.dist-info/METADATA
opinion_api-0.3.0.dist-info/WHEEL
opinion_api-0.3.0.dist-info/top_level.txt
opinion_api-0.3.0.dist-info/RECORD
