Metadata-Version: 2.4
Name: opinion-api
Version: 0.3.0
Summary: Opinion Prediction Market API
Home-page: https://opinion.trade
Author: Opinion Team
Author-email: Opinion Team <support@opinion.trade>
License-Expression: MIT
Project-URL: Repository, https://github.com/opinionlabs/openapi
Keywords: OpenAPI,Opinion,Prediction Market API,opinion.trade
Requires-Python: >=3.9
Requires-Dist: urllib3<3.0.0,>=2.1.0
Requires-Dist: python-dateutil>=2.8.2
Requires-Dist: pydantic>=2
Requires-Dist: typing-extensions>=4.7.1
Dynamic: author
Dynamic: home-page
